pybrcode/__init__.py
pybrcode/exceptions.py
pybrcode/pix.py
pybrcode/qrcode.py
pybrcode-1.1.dist-info/LICENSE
pybrcode-1.1.dist-info/METADATA
pybrcode-1.1.dist-info/WHEEL
pybrcode-1.1.dist-info/top_level.txt
pybrcode-1.1.dist-info/RECORD
