Metadata-Version: 2.1
Name: pybrcode
Version: 1.1
Summary: Generate Pix QRCodes with any type of key
Author: viniciusmacielf (Vinícius Fonseca Maciel)
Author-email: <viniciusmacielf@gmail.com>
Keywords: python,pix,qrcode,brcode,svg pix qrcode
Classifier: Intended Audience :: Developers
Classifier: Programming Language :: Python :: 3
Classifier: License :: OSI Approved :: MIT License
Classifier: Operating System :: OS Independent
Requires-Python: >=3.6
License-File: LICENSE
Requires-Dist: crcmod
Requires-Dist: qrcode
Requires-Dist: Unidecode
